elmsdk/__init__.py
elmsdk/sdk.py
elmsdk/configuration/__init__.py
elmsdk/configuration/settings.py
elmsdk/utilities/__init__.py
elmsdk/utilities/api.py
elmsdk/utilities/base_functions.py
elmsdk/utilities/storage.py
elmsdk-0.3.4.dist-info/LICENSE
elmsdk-0.3.4.dist-info/METADATA
elmsdk-0.3.4.dist-info/WHEEL
elmsdk-0.3.4.dist-info/top_level.txt
elmsdk-0.3.4.dist-info/RECORD
