Metadata-Version: 2.1
Name: elmsdk
Version: 0.3.4
Summary: SDK for running docker containers on elmware
Home-page: https://github.com/elmware/elmware-sdk
Author: Elmware
Author-email: support@elmware.com
License: MIT
Platform: UNKNOWN
Classifier: Programming Language :: Python :: 3
Classifier: License :: OSI Approved :: MIT License
Classifier: Operating System :: OS Independent
Requires-Dist: requests
